[
  {
    "trend_arrow": "FLAT", 
    "display_time": "2017-05-19T22:08:04-07:00", 
    "noise": 1, 
    "system_time": "2017-05-20T03:56:47-07:00", 
    "direction": "Flat", 
    "sgv": 93, 
    "dateString": "2017-05-19T22:08:04-07:00", 
    "date": 1495256884000, 
    "unfiltered": 89200, 
    "filtered": 94064, 
    "device": "openaps://indy-ex2/cgm", 
    "rssi": 197, 
    "type": "sgv", 
    "glucose": 93
  }, 
  {
    "trend_arrow": "FLAT", 
    "display_time": "2017-05-19T22:03:04-07:00", 
    "noise": 1, 
    "system_time": "2017-05-20T03:51:47-07:00", 
    "direction": "Flat", 
    "sgv": 91, 
    "dateString": "2017-05-19T22:03:04-07:00", 
    "date": 1495256584000, 
    "unfiltered": 88080, 
    "filtered": 97456, 
    "device": "openaps://indy-ex2/cgm", 
    "rssi": 198, 
    "type": "sgv", 
    "glucose": 91
  }
]