[
  {
    "trend_arrow": "FLAT", 
    "display_time": "2017-05-18T03:23:08-07:00", 
    "noise": 1, 
    "system_time": "2017-05-18T11:23:03-07:00", 
    "direction": "Flat", 
    "sgv": 84, 
    "dateString": "2017-05-18T03:23:08-07:00", 
    "date": 1495102988000, 
    "unfiltered": 95024, 
    "filtered": 98704, 
    "device": "openaps://indy-ex2/cgm", 
    "rssi": 186, 
    "type": "sgv", 
    "glucose": 84
  }, 
  {
    "trend_arrow": "FLAT", 
    "display_time": "2017-05-18T03:18:08-07:00", 
    "noise": 1, 
    "system_time": "2017-05-18T11:18:03-07:00", 
    "direction": "Flat", 
    "sgv": 87, 
    "dateString": "2017-05-18T03:18:08-07:00", 
    "date": 1495102688000, 
    "unfiltered": 97184, 
    "filtered": 100672, 
    "device": "openaps://indy-ex2/cgm", 
    "rssi": 186, 
    "type": "sgv", 
    "glucose": 87
  }
]