[
  {
    "trend_arrow": "FLAT", 
    "display_time": "2017-05-23T22:48:19-07:00", 
    "noise": 1, 
    "system_time": "2017-05-24T06:48:14-07:00", 
    "direction": "Flat", 
    "sgv": 150, 
    "dateString": "2017-05-23T22:48:19-07:00", 
    "date": 1495604899000, 
    "unfiltered": 139072, 
    "filtered": 131680, 
    "device": "openaps://indy-ex2/cgm", 
    "rssi": 187, 
    "type": "sgv", 
    "glucose": 150
  }, 
  {
    "trend_arrow": "FLAT", 
    "display_time": "2017-05-23T22:43:19-07:00", 
    "noise": 1, 
    "system_time": "2017-05-24T06:43:14-07:00", 
    "direction": "Flat", 
    "sgv": 144, 
    "dateString": "2017-05-23T22:43:19-07:00", 
    "date": 1495604599000, 
    "unfiltered": 133856, 
    "filtered": 127104, 
    "device": "openaps://indy-ex2/cgm", 
    "rssi": 186, 
    "type": "sgv", 
    "glucose": 144
  }
]