[
  {
    "trend_arrow": "FLAT", 
    "display_time": "2017-05-23T16:03:22-07:00", 
    "noise": 1, 
    "system_time": "2017-05-24T00:03:16-07:00", 
    "direction": "Flat", 
    "sgv": 75, 
    "dateString": "2017-05-23T16:03:22-07:00", 
    "date": 1495580602000, 
    "unfiltered": 70304, 
    "filtered": 68928, 
    "device": "openaps://indy-ex2/cgm", 
    "rssi": 938, 
    "type": "sgv", 
    "glucose": 75
  }, 
  {
    "trend_arrow": "NOT_COMPUTABLE", 
    "display_time": "2017-05-23T15:58:20-07:00", 
    "noise": 1, 
    "system_time": "2017-05-23T23:58:15-07:00", 
    "direction": "NOT COMPUTABLE", 
    "sgv": 75, 
    "dateString": "2017-05-23T15:58:20-07:00", 
    "date": 1495580300000, 
    "unfiltered": 70080, 
    "filtered": 68688, 
    "device": "openaps://indy-ex2/cgm", 
    "rssi": 198, 
    "type": "sgv", 
    "glucose": 75
  }
]