[
  {
    "trend_arrow": "45_DOWN", 
    "display_time": "2017-05-19T17:23:05-07:00", 
    "noise": 1, 
    "system_time": "2017-05-19T23:11:49-07:00", 
    "direction": "FortyFiveDown", 
    "sgv": 131, 
    "dateString": "2017-05-19T17:23:05-07:00", 
    "device": "openaps://indy-ex2/cgm", 
    "unfiltered": 114368, 
    "rssi": 436, 
    "date": 1495239785000, 
    "filtered": 119584, 
    "type": "sgv", 
    "glucose": 131
  }, 
  {
    "trend_arrow": "45_DOWN", 
    "display_time": "2017-05-19T17:18:05-07:00", 
    "noise": 1, 
    "system_time": "2017-05-19T23:06:48-07:00", 
    "direction": "FortyFiveDown", 
    "sgv": 134, 
    "dateString": "2017-05-19T17:18:05-07:00", 
    "device": "openaps://indy-ex2/cgm", 
    "unfiltered": 115840, 
    "rssi": 188, 
    "date": 1495239485000, 
    "filtered": 123440, 
    "type": "sgv", 
    "glucose": 134
  }
]