[
  {
    "trend_arrow": "FLAT", 
    "display_time": "2017-05-22T00:33:24-07:00", 
    "noise": 1, 
    "system_time": "2017-05-22T08:33:19-07:00", 
    "direction": "Flat", 
    "sgv": 135, 
    "dateString": "2017-05-22T00:33:24-07:00", 
    "device": "openaps://indy-ex2/cgm", 
    "unfiltered": 142816, 
    "rssi": 193, 
    "date": 1495438404000, 
    "filtered": 136768, 
    "type": "sgv", 
    "glucose": 135
  }, 
  {
    "trend_arrow": "FLAT", 
    "display_time": "2017-05-22T00:28:24-07:00", 
    "noise": 1, 
    "system_time": "2017-05-22T08:28:19-07:00", 
    "direction": "Flat", 
    "sgv": 133, 
    "dateString": "2017-05-22T00:28:24-07:00", 
    "device": "openaps://indy-ex2/cgm", 
    "unfiltered": 141184, 
    "rssi": 192, 
    "date": 1495438104000, 
    "filtered": 132640, 
    "type": "sgv", 
    "glucose": 133
  }
]