[
  {
    "trend_arrow": "FLAT", 
    "display_time": "2017-05-23T21:38:19-07:00", 
    "noise": 1, 
    "direction": "Flat", 
    "system_time": "2017-05-24T05:38:14-07:00", 
    "sgv": 95, 
    "dateString": "2017-05-23T21:38:19-07:00", 
    "device": "openaps://indy-ex2/cgm", 
    "unfiltered": 89600, 
    "rssi": 188, 
    "date": 1495600699000.0, 
    "filtered": 95424, 
    "type": "sgv", 
    "glucose": 95
  }, 
  {
    "trend_arrow": "FLAT", 
    "display_time": "2017-05-23T21:33:20-07:00", 
    "noise": 1, 
    "direction": "Flat", 
    "system_time": "2017-05-24T05:33:14-07:00", 
    "sgv": 98, 
    "dateString": "2017-05-23T21:33:20-07:00", 
    "device": "openaps://indy-ex2/cgm", 
    "unfiltered": 92752, 
    "rssi": 188, 
    "date": 1495600400000.0, 
    "filtered": 95440, 
    "type": "sgv", 
    "glucose": 98
  }, 
  {
    "trend_arrow": "FLAT", 
    "display_time": "2017-05-23T21:28:21-07:00", 
    "noise": 1, 
    "direction": "Flat", 
    "system_time": "2017-05-24T05:28:15-07:00", 
    "sgv": 104, 
    "dateString": "2017-05-23T21:28:21-07:00", 
    "device": "openaps://indy-ex2/cgm", 
    "unfiltered": 98272, 
    "rssi": 931, 
    "date": 1495600101000.0, 
    "filtered": 93904, 
    "type": "sgv", 
    "glucose": 104
  }, 
  {
    "trend_arrow": "FLAT", 
    "display_time": "2017-05-23T21:23:19-07:00", 
    "noise": 1, 
    "direction": "Flat", 
    "system_time": "2017-05-24T05:23:14-07:00", 
    "sgv": 101, 
    "dateString": "2017-05-23T21:23:19-07:00", 
    "device": "openaps://indy-ex2/cgm", 
    "unfiltered": 95456, 
    "rssi": 185, 
    "date": 1495599799000.0, 
    "filtered": 92384, 
    "type": "sgv", 
    "glucose": 101
  }, 
  {
    "trend_arrow": "FLAT", 
    "display_time": "2017-05-23T21:18:20-07:00", 
    "noise": 1, 
    "direction": "Flat", 
    "system_time": "2017-05-24T05:18:14-07:00", 
    "sgv": 98, 
    "dateString": "2017-05-23T21:18:20-07:00", 
    "device": "openaps://indy-ex2/cgm", 
    "unfiltered": 92960, 
    "rssi": 193, 
    "date": 1495599500000.0, 
    "filtered": 92032, 
    "type": "sgv", 
    "glucose": 98
  }, 
  {
    "trend_arrow": "FLAT", 
    "display_time": "2017-05-23T21:13:19-07:00", 
    "noise": 1, 
    "direction": "Flat", 
    "system_time": "2017-05-24T05:13:14-07:00", 
    "sgv": 97, 
    "dateString": "2017-05-23T21:13:19-07:00", 
    "device": "openaps://indy-ex2/cgm", 
    "unfiltered": 92144, 
    "rssi": 199, 
    "date": 1495599199000.0, 
    "filtered": 92784, 
    "type": "sgv", 
    "glucose": 97
  }
]