[
  {
    "trend_arrow": "FLAT", 
    "display_time": "2017-05-21T14:08:26-07:00", 
    "noise": 1, 
    "direction": "Flat", 
    "system_time": "2017-05-21T22:08:20-07:00", 
    "sgv": 84, 
    "dateString": "2017-05-21T14:08:26-07:00", 
    "device": "openaps://indy-ex2/cgm", 
    "unfiltered": 106832, 
    "rssi": 195, 
    "date": 1495400906000.0, 
    "filtered": 99632, 
    "type": "sgv", 
    "glucose": 84
  }, 
  {
    "trend_arrow": "NOT_COMPUTABLE", 
    "display_time": "2017-05-21T14:03:26-07:00", 
    "noise": 1, 
    "direction": "NOT COMPUTABLE", 
    "system_time": "2017-05-21T22:03:20-07:00", 
    "sgv": 77, 
    "dateString": "2017-05-21T14:03:26-07:00", 
    "device": "openaps://indy-ex2/cgm", 
    "unfiltered": 99568, 
    "rssi": 177, 
    "date": 1495400606000.0, 
    "filtered": 99968, 
    "type": "sgv", 
    "glucose": 77
  }, 
  {
    "trend_arrow": "NOT_COMPUTABLE", 
    "display_time": "2017-05-21T13:58:26-07:00", 
    "noise": 1, 
    "direction": "NOT COMPUTABLE", 
    "system_time": "2017-05-21T21:58:20-07:00", 
    "sgv": 77, 
    "dateString": "2017-05-21T13:58:26-07:00", 
    "device": "openaps://indy-ex2/cgm", 
    "unfiltered": 99824, 
    "rssi": 199, 
    "date": 1495400306000.0, 
    "filtered": 101984, 
    "type": "sgv", 
    "glucose": 77
  }, 
  {
    "trend_arrow": "FLAT", 
    "display_time": "2017-05-21T13:48:26-07:00", 
    "noise": 1, 
    "direction": "Flat", 
    "system_time": "2017-05-21T21:48:21-07:00", 
    "sgv": 80, 
    "dateString": "2017-05-21T13:48:26-07:00", 
    "device": "openaps://indy-ex2/cgm", 
    "unfiltered": 102656, 
    "rssi": 425, 
    "date": 1495399706000.0, 
    "filtered": 104352, 
    "type": "sgv", 
    "glucose": 80
  }, 
  {
    "trend_arrow": "FLAT", 
    "display_time": "2017-05-21T13:43:26-07:00", 
    "noise": 1, 
    "direction": "Flat", 
    "system_time": "2017-05-21T21:43:20-07:00", 
    "sgv": 82, 
    "dateString": "2017-05-21T13:43:26-07:00", 
    "device": "openaps://indy-ex2/cgm", 
    "unfiltered": 105088, 
    "rssi": 168, 
    "date": 1495399406000.0, 
    "filtered": 104368, 
    "type": "sgv", 
    "glucose": 82
  }
]