[
  {
    "trend_arrow": "FLAT", 
    "display_time": "2017-05-22T22:28:22-07:00", 
    "noise": 1, 
    "system_time": "2017-05-23T06:28:17-07:00", 
    "direction": "Flat", 
    "sgv": 133, 
    "dateString": "2017-05-22T22:28:22-07:00", 
    "device": "openaps://indy-ex2/cgm", 
    "unfiltered": 128240, 
    "rssi": 188, 
    "date": 1495517302000, 
    "filtered": 123264, 
    "type": "sgv", 
    "glucose": 133
  }, 
  {
    "trend_arrow": "FLAT", 
    "display_time": "2017-05-22T22:23:22-07:00", 
    "noise": 1, 
    "system_time": "2017-05-23T06:23:17-07:00", 
    "direction": "Flat", 
    "sgv": 126, 
    "dateString": "2017-05-22T22:23:22-07:00", 
    "device": "openaps://indy-ex2/cgm", 
    "unfiltered": 122032, 
    "rssi": 189, 
    "date": 1495517002000, 
    "filtered": 123648, 
    "type": "sgv", 
    "glucose": 126
  }
]