[
  {
    "trend_arrow": "FLAT", 
    "display_time": "2017-05-16T03:18:13-07:00", 
    "noise": 1, 
    "system_time": "2017-05-16T11:18:08-07:00", 
    "direction": "Flat", 
    "sgv": 137, 
    "dateString": "2017-05-16T03:18:13-07:00", 
    "device": "openaps://indy-ex2/cgm", 
    "unfiltered": 143168, 
    "rssi": 186, 
    "date": 1494929893000, 
    "filtered": 146016, 
    "type": "sgv", 
    "glucose": 137
  }, 
  {
    "trend_arrow": "FLAT", 
    "display_time": "2017-05-16T03:13:13-07:00", 
    "noise": 1, 
    "system_time": "2017-05-16T11:13:08-07:00", 
    "direction": "Flat", 
    "sgv": 140, 
    "dateString": "2017-05-16T03:13:13-07:00", 
    "device": "openaps://indy-ex2/cgm", 
    "unfiltered": 145664, 
    "rssi": 188, 
    "date": 1494929593000, 
    "filtered": 146976, 
    "type": "sgv", 
    "glucose": 140
  }
]