[
  {
    "trend_arrow": "FLAT", 
    "display_time": "2017-05-20T23:03:28-07:00", 
    "noise": 1, 
    "direction": "Flat", 
    "system_time": "2017-05-21T07:03:22-07:00", 
    "sgv": 78, 
    "dateString": "2017-05-20T23:03:28-07:00", 
    "device": "openaps://indy-ex2/cgm", 
    "unfiltered": 97728, 
    "rssi": 448, 
    "date": 1495346608000.0, 
    "filtered": 93088, 
    "type": "sgv", 
    "glucose": 78
  }, 
  {
    "trend_arrow": "FLAT", 
    "display_time": "2017-05-20T22:58:27-07:00", 
    "noise": 1, 
    "direction": "Flat", 
    "system_time": "2017-05-21T06:58:22-07:00", 
    "sgv": 70, 
    "dateString": "2017-05-20T22:58:27-07:00", 
    "device": "openaps://indy-ex2/cgm", 
    "unfiltered": 90160, 
    "rssi": 183, 
    "date": 1495346307000.0, 
    "filtered": 90704, 
    "type": "sgv", 
    "glucose": 70
  }, 
  {
    "trend_arrow": "FLAT", 
    "display_time": "2017-05-20T22:53:27-07:00", 
    "noise": 1, 
    "direction": "Flat", 
    "system_time": "2017-05-21T06:53:22-07:00", 
    "sgv": 72, 
    "dateString": "2017-05-20T22:53:27-07:00", 
    "device": "openaps://indy-ex2/cgm", 
    "unfiltered": 91344, 
    "rssi": 189, 
    "date": 1495346007000.0, 
    "filtered": 86640, 
    "type": "sgv", 
    "glucose": 72
  }, 
  {
    "trend_arrow": "FLAT", 
    "display_time": "2017-05-20T22:48:27-07:00", 
    "noise": 1, 
    "direction": "Flat", 
    "system_time": "2017-05-21T06:48:22-07:00", 
    "sgv": 71, 
    "dateString": "2017-05-20T22:48:27-07:00", 
    "device": "openaps://indy-ex2/cgm", 
    "unfiltered": 91040, 
    "rssi": 180, 
    "date": 1495345707000.0, 
    "filtered": 82144, 
    "type": "sgv", 
    "glucose": 71
  }, 
  {
    "trend_arrow": "FLAT", 
    "display_time": "2017-05-20T22:43:27-07:00", 
    "noise": 1, 
    "direction": "Flat", 
    "system_time": "2017-05-21T06:43:22-07:00", 
    "sgv": 67, 
    "dateString": "2017-05-20T22:43:27-07:00", 
    "device": "openaps://indy-ex2/cgm", 
    "unfiltered": 86736, 
    "rssi": 185, 
    "date": 1495345407000.0, 
    "filtered": 80272, 
    "type": "sgv", 
    "glucose": 67
  }, 
  {
    "trend_arrow": "FLAT", 
    "display_time": "2017-05-20T22:38:27-07:00", 
    "noise": 1, 
    "direction": "Flat", 
    "system_time": "2017-05-21T06:38:22-07:00", 
    "sgv": 62, 
    "dateString": "2017-05-20T22:38:27-07:00", 
    "device": "openaps://indy-ex2/cgm", 
    "unfiltered": 81392, 
    "rssi": 186, 
    "date": 1495345107000.0, 
    "filtered": 82432, 
    "type": "sgv", 
    "glucose": 62
  }
]