[
  {
    "trend_arrow": "FLAT", 
    "system_time": "2017-05-23T15:38:16", 
    "noise": 1, 
    "direction": "Flat", 
    "sgv": 110, 
    "display_time": "2017-05-23T07:38:21", 
    "date": 1495550301000.0, 
    "dateString": "2017-05-23T07:38:21", 
    "unfiltered": 103792, 
    "filtered": 97504, 
    "device": "openaps://indy-ex2/cgm", 
    "rssi": 191, 
    "type": "sgv", 
    "glucose": 110
  }, 
  {
    "trend_arrow": "FLAT", 
    "system_time": "2017-05-23T15:33:15", 
    "noise": 1, 
    "direction": "Flat", 
    "sgv": 106, 
    "display_time": "2017-05-23T07:33:21", 
    "date": 1495550001000.0, 
    "dateString": "2017-05-23T07:33:21", 
    "unfiltered": 100416, 
    "filtered": 95648, 
    "device": "openaps://indy-ex2/cgm", 
    "rssi": 194, 
    "type": "sgv", 
    "glucose": 106
  }, 
  {
    "trend_arrow": "FLAT", 
    "system_time": "2017-05-23T15:28:16", 
    "noise": 1, 
    "direction": "Flat", 
    "sgv": 102, 
    "display_time": "2017-05-23T07:28:21", 
    "date": 1495549701000.0, 
    "dateString": "2017-05-23T07:28:21", 
    "unfiltered": 96048, 
    "filtered": 95344, 
    "device": "openaps://indy-ex2/cgm", 
    "rssi": 195, 
    "type": "sgv", 
    "glucose": 102
  }, 
  {
    "trend_arrow": "FLAT", 
    "system_time": "2017-05-23T15:23:16", 
    "noise": 1, 
    "direction": "Flat", 
    "sgv": 99, 
    "display_time": "2017-05-23T07:23:21", 
    "date": 1495549401000.0, 
    "dateString": "2017-05-23T07:23:21", 
    "unfiltered": 94000, 
    "filtered": 95936, 
    "device": "openaps://indy-ex2/cgm", 
    "rssi": 196, 
    "type": "sgv", 
    "glucose": 99
  }, 
  {
    "trend_arrow": "FLAT", 
    "system_time": "2017-05-23T15:18:16", 
    "noise": 1, 
    "direction": "Flat", 
    "sgv": 101, 
    "display_time": "2017-05-23T07:18:21", 
    "date": 1495549101000.0, 
    "dateString": "2017-05-23T07:18:21", 
    "unfiltered": 95744, 
    "filtered": 97328, 
    "device": "openaps://indy-ex2/cgm", 
    "rssi": 197, 
    "type": "sgv", 
    "glucose": 101
  }
]