[
  {
    "trend_arrow": "FLAT", 
    "display_time": "2017-05-18T20:38:08-07:00", 
    "noise": 1, 
    "system_time": "2017-05-19T02:26:51-07:00", 
    "direction": "Flat", 
    "sgv": 134, 
    "dateString": "2017-05-18T20:38:08-07:00", 
    "device": "openaps://indy-ex2/cgm", 
    "unfiltered": 129792, 
    "rssi": 172, 
    "date": 1495165088000, 
    "filtered": 134976, 
    "type": "sgv", 
    "glucose": 134
  }, 
  {
    "trend_arrow": "FLAT", 
    "display_time": "2017-05-18T20:33:08-07:00", 
    "noise": 1, 
    "system_time": "2017-05-19T02:21:51-07:00", 
    "direction": "Flat", 
    "sgv": 139, 
    "dateString": "2017-05-18T20:33:08-07:00", 
    "device": "openaps://indy-ex2/cgm", 
    "unfiltered": 133984, 
    "rssi": 191, 
    "date": 1495164788000, 
    "filtered": 137152, 
    "type": "sgv", 
    "glucose": 139
  }
]