[
  {
    "trend_arrow": "FLAT", 
    "system_time": "2017-05-24T07:18:14", 
    "noise": 1, 
    "direction": "Flat", 
    "sgv": 184, 
    "display_time": "2017-05-23T23:18:19", 
    "date": 1495606699000.0, 
    "dateString": "2017-05-23T23:18:19", 
    "unfiltered": 168576, 
    "filtered": 162944, 
    "device": "openaps://indy-ex2/cgm", 
    "rssi": 183, 
    "type": "sgv", 
    "glucose": 184
  }, 
  {
    "trend_arrow": "45_UP", 
    "system_time": "2017-05-24T07:13:14", 
    "noise": 1, 
    "direction": "FortyFiveUp", 
    "sgv": 180, 
    "display_time": "2017-05-23T23:13:19", 
    "date": 1495606399000.0, 
    "dateString": "2017-05-23T23:13:19", 
    "unfiltered": 165184, 
    "filtered": 158208, 
    "device": "openaps://indy-ex2/cgm", 
    "rssi": 184, 
    "type": "sgv", 
    "glucose": 180
  }, 
  {
    "trend_arrow": "45_UP", 
    "system_time": "2017-05-24T07:08:14", 
    "noise": 1, 
    "direction": "FortyFiveUp", 
    "sgv": 175, 
    "display_time": "2017-05-23T23:08:19", 
    "date": 1495606099000.0, 
    "dateString": "2017-05-23T23:08:19", 
    "unfiltered": 160960, 
    "filtered": 152832, 
    "device": "openaps://indy-ex2/cgm", 
    "rssi": 187, 
    "type": "sgv", 
    "glucose": 175
  }, 
  {
    "trend_arrow": "45_UP", 
    "system_time": "2017-05-24T07:03:14", 
    "noise": 1, 
    "direction": "FortyFiveUp", 
    "sgv": 170, 
    "display_time": "2017-05-23T23:03:19", 
    "date": 1495605799000.0, 
    "dateString": "2017-05-23T23:03:19", 
    "unfiltered": 155808, 
    "filtered": 147136, 
    "device": "openaps://indy-ex2/cgm", 
    "rssi": 187, 
    "type": "sgv", 
    "glucose": 170
  }, 
  {
    "trend_arrow": "45_UP", 
    "system_time": "2017-05-24T06:58:14", 
    "noise": 1, 
    "direction": "FortyFiveUp", 
    "sgv": 163, 
    "display_time": "2017-05-23T22:58:19", 
    "date": 1495605499000.0, 
    "dateString": "2017-05-23T22:58:19", 
    "unfiltered": 150432, 
    "filtered": 141504, 
    "device": "openaps://indy-ex2/cgm", 
    "rssi": 186, 
    "type": "sgv", 
    "glucose": 163
  }, 
  {
    "trend_arrow": "45_UP", 
    "system_time": "2017-05-24T06:53:14", 
    "noise": 1, 
    "direction": "FortyFiveUp", 
    "sgv": 157, 
    "display_time": "2017-05-23T22:53:19", 
    "date": 1495605199000.0, 
    "dateString": "2017-05-23T22:53:19", 
    "unfiltered": 144864, 
    "filtered": 136352, 
    "device": "openaps://indy-ex2/cgm", 
    "rssi": 187, 
    "type": "sgv", 
    "glucose": 157
  }
]