[
  {
    "trend_arrow": "FLAT", 
    "display_time": "2017-05-24T03:38:19-07:00", 
    "noise": 1, 
    "system_time": "2017-05-24T11:38:13-07:00", 
    "direction": "Flat", 
    "sgv": 170, 
    "dateString": "2017-05-24T03:38:19-07:00", 
    "device": "openaps://indy-ex2/cgm", 
    "unfiltered": 156448, 
    "rssi": 191, 
    "date": 1495622299000, 
    "filtered": 158144, 
    "type": "sgv", 
    "glucose": 170
  }, 
  {
    "trend_arrow": "FLAT", 
    "display_time": "2017-05-24T03:33:19-07:00", 
    "noise": 1, 
    "system_time": "2017-05-24T11:33:13-07:00", 
    "direction": "Flat", 
    "sgv": 172, 
    "dateString": "2017-05-24T03:33:19-07:00", 
    "device": "openaps://indy-ex2/cgm", 
    "unfiltered": 157760, 
    "rssi": 191, 
    "date": 1495621999000, 
    "filtered": 158624, 
    "type": "sgv", 
    "glucose": 172
  }
]